{
  "updated_at": "2026-06-12T16:18:54.253953Z",
  "trade_date": "2026-06-12",
  "spot": 1.9182,
  "count": 19,
  "data": [
    {
      "month": "2026-06",
      "label": "Jun 26",
      "settle": 1.9182,
      "volume": 39
    },
    {
      "month": "2026-07",
      "label": "Jul 26",
      "settle": 1.723,
      "volume": 27
    },
    {
      "month": "2026-08",
      "label": "Aug 26",
      "settle": 1.5895,
      "volume": 46
    },
    {
      "month": "2026-09",
      "label": "Sep 26",
      "settle": 1.55,
      "volume": 25
    },
    {
      "month": "2026-10",
      "label": "Oct 26",
      "settle": 1.5312,
      "volume": 26
    },
    {
      "month": "2026-11",
      "label": "Nov 26",
      "settle": 1.525,
      "volume": 12
    },
    {
      "month": "2026-12",
      "label": "Dec 26",
      "settle": 1.525,
      "volume": 8
    },
    {
      "month": "2027-01",
      "label": "Jan 27",
      "settle": 1.52,
      "volume": 6
    },
    {
      "month": "2027-02",
      "label": "Feb 27",
      "settle": 1.52,
      "volume": 6
    },
    {
      "month": "2027-03",
      "label": "Mar 27",
      "settle": 1.4965,
      "volume": 2
    },
    {
      "month": "2027-04",
      "label": "Apr 27",
      "settle": 1.4768,
      "volume": 2
    },
    {
      "month": "2027-05",
      "label": "May 27",
      "settle": 1.4785,
      "volume": 1
    },
    {
      "month": "2027-06",
      "label": "Jun 27",
      "settle": 1.49,
      "volume": 1
    },
    {
      "month": "2027-07",
      "label": "Jul 27",
      "settle": 1.435,
      "volume": 1
    },
    {
      "month": "2027-08",
      "label": "Aug 27",
      "settle": 1.4715,
      "volume": 14
    },
    {
      "month": "2027-09",
      "label": "Sep 27",
      "settle": 1.49,
      "volume": 4
    },
    {
      "month": "2027-10",
      "label": "Oct 27",
      "settle": 1.49,
      "volume": 5
    },
    {
      "month": "2027-11",
      "label": "Nov 27",
      "settle": 1.48,
      "volume": 3
    },
    {
      "month": "2027-12",
      "label": "Dec 27",
      "settle": 1.48,
      "volume": 1
    }
  ]
}